willump/__init__.py
willump/live_events.py
willump/nunu.py
willump/proc_utils.py
willump/subscription.py
willump/willump.py
willump-1.4.0.dist-info/LICENSE
willump-1.4.0.dist-info/METADATA
willump-1.4.0.dist-info/WHEEL
willump-1.4.0.dist-info/top_level.txt
willump-1.4.0.dist-info/RECORD
