Metadata-Version: 2.1
Name: willump
Version: 1.4.0
Summary: Willump is a Python3 helper for the League of Legends LCU API
Home-page: https://github.com/elliejs/Willump
Author: elliejs
Author-email: ejsilver@wpi.edu
Project-URL: Bug Reports, https://github.com/elliejs/Willump/issues
Project-URL: Source, https://github.com/elliejs/Willump
Keywords: api,wamp,rest,websocket,server,ssl
Classifier: Development Status :: 3 - Alpha
Classifier: Intended Audience :: Developers
Classifier: License :: OSI Approved :: MIT License
Classifier: Programming Language :: Python :: 3
Classifier: Programming Language :: Python :: 3.7
Classifier: Programming Language :: Python :: 3.8
Classifier: Programming Language :: Python :: 3.9
Classifier: Programming Language :: Python :: 3 :: Only
Requires-Python: >=3.7, <4
License-File: LICENSE
Requires-Dist: psutil
Requires-Dist: aiohttp
Requires-Dist: cryptography
Provides-Extra: dev
Requires-Dist: check-manifest ; extra == 'dev'
Provides-Extra: test
Requires-Dist: coverage ; extra == 'test'
